efipay/__init__.py
efipay/constants.py
efipay/efipay.py
efipay/endpoints.py
efipay/exceptions.py
efipay/version.py
efipay-1.0.6.dist-info/licenses/LICENSE
test/__init__.py
test/test_efipay.py
efipay-1.0.6.dist-info/METADATA
efipay-1.0.6.dist-info/WHEEL
efipay-1.0.6.dist-info/top_level.txt
efipay-1.0.6.dist-info/RECORD
